<?xml version="1.1" encoding="UTF-8"?>
<expression:EMFExpression xmi:version="2.0" xmlns:xmi="http://www.omg.org/XMI" xmlns:expression="http:///expression.ecore" id="tMap_1=>" expression="(((PosOrderLine.price_unit + (PosOrderLine.price_unit * PosOrder.amount_tax) - PosOrderLine.price_unit * PosOrderLine.discount) * PosOrderLine.qty) - PosOrderLine.price_unit) * PosOrderLine.qty">
  <variables name="DimProduct.product_key" value="null" talendType="id_Integer" nullable="true"/>
  <variables name="DimProduct.attribute_group_key" value="null" talendType="id_Integer" nullable="true"/>
  <variables name="DimProduct.product_name" value="null" talendType="id_String" nullable="true"/>
  <variables name="DimProduct.product_description" value="null" talendType="id_String" nullable="true"/>
  <variables name="DimProduct.category" value="null" talendType="id_String" nullable="true"/>
  <variables name="DimProduct.category_description" value="null" talendType="id_String" nullable="true"/>
  <variables name="DimProduct.weight" value="null" talendType="id_Integer" nullable="true"/>
  <variables name="DimProduct.volume" value="null" talendType="id_String" nullable="true"/>
  <variables name="DimProduct.barcode" value="null" talendType="id_String" nullable="true"/>
  <variables name="DimProduct.product_code" value="null" talendType="id_String" nullable="true"/>
  <variables name="DimCustomer.customer_key" value="null" talendType="id_Integer" nullable="true"/>
  <variables name="DimCustomer.name" value="null" talendType="id_String" nullable="true"/>
  <variables name="DimCustomer.country" value="null" talendType="id_String" nullable="true"/>
  <variables name="DimCustomer.company" value="null" talendType="id_String" nullable="true"/>
  <variables name="DimCustomer.street" value="null" talendType="id_String" nullable="true"/>
  <variables name="DimCustomer.street_2" value="null" talendType="id_String" nullable="true"/>
  <variables name="DimCustomer.city" value="null" talendType="id_String" nullable="true"/>
  <variables name="DimCustomer.state" value="null" talendType="id_String" nullable="true"/>
  <variables name="DimStore.store_key" value="null" talendType="id_Integer" nullable="true"/>
  <variables name="DimStore.name" value="null" talendType="id_String" nullable="true"/>
  <variables name="DimPayment.payment_method_key" value="null" talendType="id_Integer" nullable="true"/>
  <variables name="DimPayment.name" value="null" talendType="id_String" nullable="true"/>
  <variables name="DimPayment.isCash" value="null" talendType="id_Boolean" nullable="true"/>
  <variables name="PosOrderLine.id" value="null" talendType="id_Integer" nullable="true"/>
  <variables name="PosOrderLine.company_id" value="null" talendType="id_Integer" nullable="true"/>
  <variables name="PosOrderLine.name" value="null" talendType="id_String" nullable="true"/>
  <variables name="PosOrderLine.notice" value="null" talendType="id_String" nullable="true"/>
  <variables name="PosOrderLine.product_id" value="null" talendType="id_Integer" nullable="true"/>
  <variables name="PosOrderLine.price_unit" value="null" talendType="id_Integer" nullable="true"/>
  <variables name="PosOrderLine.qty" value="null" talendType="id_Integer" nullable="true"/>
  <variables name="PosOrderLine.price_subtotal" value="null" talendType="id_Integer" nullable="true"/>
  <variables name="PosOrderLine.price_subtotal_incl" value="null" talendType="id_Integer" nullable="true"/>
  <variables name="PosOrderLine.total_cost" value="null" talendType="id_String" nullable="true"/>
  <variables name="PosOrderLine.is_total_cost_computed" value="null" talendType="id_Boolean" nullable="true"/>
  <variables name="PosOrderLine.discount" value="null" talendType="id_Integer" nullable="true"/>
  <variables name="PosOrderLine.order_id" value="null" talendType="id_Integer" nullable="true"/>
  <variables name="PosOrderLine.full_product_name" value="null" talendType="id_String" nullable="true"/>
  <variables name="PosOrderLine.customer_note" value="null" talendType="id_String" nullable="true"/>
  <variables name="PosOrderLine.refunded_orderline_id" value="null" talendType="id_String" nullable="true"/>
  <variables name="PosOrderLine.create_uid" value="null" talendType="id_Integer" nullable="true"/>
  <variables name="PosOrderLine.create_date" value="null" talendType="id_Date" nullable="true"/>
  <variables name="PosOrderLine.write_uid" value="null" talendType="id_Integer" nullable="true"/>
  <variables name="PosOrderLine.write_date" value="null" talendType="id_Date" nullable="true"/>
  <variables name="PosOrderLine.sale_order_origin_id" value="null" talendType="id_String" nullable="true"/>
  <variables name="PosOrderLine.sale_order_line_id" value="null" talendType="id_String" nullable="true"/>
  <variables name="PosOrderLine.down_payment_details" value="null" talendType="id_String" nullable="true"/>
  <variables name="PosOrder.id" value="null" talendType="id_Integer" nullable="true"/>
  <variables name="PosOrder.name" value="null" talendType="id_String" nullable="true"/>
  <variables name="PosOrder.date_order" value="null" talendType="id_Date" nullable="true"/>
  <variables name="PosOrder.user_id" value="null" talendType="id_Integer" nullable="true"/>
  <variables name="PosOrder.amount_tax" value="null" talendType="id_Integer" nullable="true"/>
  <variables name="PosOrder.amount_total" value="null" talendType="id_Integer" nullable="true"/>
  <variables name="PosOrder.amount_paid" value="null" talendType="id_Integer" nullable="true"/>
  <variables name="PosOrder.amount_return" value="null" talendType="id_Integer" nullable="true"/>
  <variables name="PosOrder.company_id" value="null" talendType="id_Integer" nullable="true"/>
  <variables name="PosOrder.pricelist_id" value="null" talendType="id_Integer" nullable="true"/>
  <variables name="PosOrder.partner_id" value="null" talendType="id_String" nullable="true"/>
  <variables name="PosOrder.sequence_number" value="null" talendType="id_Integer" nullable="true"/>
  <variables name="PosOrder.session_id" value="null" talendType="id_Integer" nullable="true"/>
  <variables name="PosOrder.currency_rate" value="null" talendType="id_Integer" nullable="true"/>
  <variables name="PosOrder.state" value="null" talendType="id_String" nullable="true"/>
  <variables name="PosOrder.account_move" value="null" talendType="id_String" nullable="true"/>
  <variables name="PosOrder.procurement_group_id" value="null" talendType="id_String" nullable="true"/>
  <variables name="PosOrder.note" value="null" talendType="id_String" nullable="true"/>
  <variables name="PosOrder.nb_print" value="null" talendType="id_Integer" nullable="true"/>
  <variables name="PosOrder.pos_reference" value="null" talendType="id_String" nullable="true"/>
  <variables name="PosOrder.sale_journal" value="null" talendType="id_Integer" nullable="true"/>
  <variables name="PosOrder.fiscal_position_id" value="null" talendType="id_String" nullable="true"/>
  <variables name="PosOrder.to_invoice" value="null" talendType="id_Boolean" nullable="true"/>
  <variables name="PosOrder.to_ship" value="null" talendType="id_Boolean" nullable="true"/>
  <variables name="PosOrder.is_tipped" value="null" talendType="id_Boolean" nullable="true"/>
  <variables name="PosOrder.tip_amount" value="null" talendType="id_Integer" nullable="true"/>
  <variables name="PosOrder.create_uid" value="null" talendType="id_Integer" nullable="true"/>
  <variables name="PosOrder.create_date" value="null" talendType="id_Date" nullable="true"/>
  <variables name="PosOrder.write_uid" value="null" talendType="id_Integer" nullable="true"/>
  <variables name="PosOrder.write_date" value="null" talendType="id_Date" nullable="true"/>
  <variables name="PosOrder.crm_team_id" value="null" talendType="id_String" nullable="true"/>
</expression:EMFExpression>
